carim_discord_bot/__init__.py
carim_discord_bot/config.py
carim_discord_bot/main.py
carim_discord_bot/managed_service.py
carim_discord_bot/message_builder.py
carim_discord_bot/setup_instructions.py
carim_discord_bot/cftools/__init__.py
carim_discord_bot/cftools/cf_cloud_service.py
carim_discord_bot/cftools/omega_service.py
carim_discord_bot/data/carim.service
carim_discord_bot/data/config.json
carim_discord_bot/data/config_descriptions.json
carim_discord_bot/discord_client/__init__.py
carim_discord_bot/discord_client/arguments.py
carim_discord_bot/discord_client/client.py
carim_discord_bot/discord_client/discord_service.py
carim_discord_bot/discord_client/member_count.py
carim_discord_bot/rcon/__init__.py
carim_discord_bot/rcon/connection.py
carim_discord_bot/rcon/protocol.py
carim_discord_bot/rcon/rcon_service.py
carim_discord_bot/rcon/registrar.py
carim_discord_bot/services/__init__.py
carim_discord_bot/services/player_count.py
carim_discord_bot/services/scheduled_command.py
carim_discord_bot/steam/__init__.py
carim_discord_bot/steam/query.py
carim_discord_bot/steam/steam_service.py
carim_discord_bot-2.2.5.dist-info/LICENSE
carim_discord_bot-2.2.5.dist-info/METADATA
carim_discord_bot-2.2.5.dist-info/WHEEL
carim_discord_bot-2.2.5.dist-info/entry_points.txt
carim_discord_bot-2.2.5.dist-info/top_level.txt
carim_discord_bot-2.2.5.dist-info/RECORD
