Metadata-Version: 2.1
Name: carim-discord-bot
Version: 2.2.5
Summary: Discord bot that provides DayZ RCon capabilities and cross chat
Home-page: https://github.com/schana/carim-discord-bot
Author: Nathaniel Schaaf
Author-email: nathaniel.schaaf@gmail.com
License: Apache Software License
Keywords: discord,dayz,rcon
Platform: any
Classifier: License :: OSI Approved :: Apache Software License
Classifier: Operating System :: OS Independent
Classifier: Programming Language :: Python
Classifier: Programming Language :: Python :: 3
Classifier: Programming Language :: Python :: 3.7
Classifier: Programming Language :: Python :: 3.8
Classifier: Programming Language :: Python :: 3.9
Requires-Python: >=3.7.*
Requires-Dist: discord.py (>=1.6.0)
Requires-Dist: requests
Provides-Extra: tests
Requires-Dist: pytest ; extra == 'tests'
Requires-Dist: pytest-timeout ; extra == 'tests'
Requires-Dist: pytest-asyncio ; extra == 'tests'
